sheets_manager/__init__.py
sheets_manager/sheets_manager.py
sheetsmanager-0.1.1.dist-info/licenses/LICENSE
sheetsmanager-0.1.1.dist-info/METADATA
sheetsmanager-0.1.1.dist-info/WHEEL
sheetsmanager-0.1.1.dist-info/top_level.txt
sheetsmanager-0.1.1.dist-info/RECORD
