Metadata-Version: 2.4
Name: sheetsmanager
Version: 0.1.1
Summary: A Python package to load and manage Google Sheets, Excel files, or any spreadsheet data from URLs and file paths.
Author: Yan Sido
Author-email: yansido1@gmail.com
Keywords: python,google-sheets,excel,spreadsheet,spreadsheet manager,sheets manager,google sheets loader,excel loader
Classifier: Development Status :: 3 - Alpha
Classifier: Intended Audience :: Developers
Classifier: Programming Language :: Python :: 3
Classifier: Operating System :: Unix
Classifier: Operating System :: MacOS :: MacOS X
Classifier: Operating System :: Microsoft :: Windows
License-File: LICENSE
Requires-Dist: pandas==2.2.3
Dynamic: author
Dynamic: author-email
Dynamic: classifier
Dynamic: description
Dynamic: description-content-type
Dynamic: keywords
Dynamic: license-file
Dynamic: requires-dist
Dynamic: summary
